pypi_sqlite_cipher/__init__.py
pypi_sqlite_cipher/pysqlite_cipher.py
pypi_sqlite_cipher/sqlcipher-shell64.exe
pypi_sqlite_cipher/新建文本文档.txt
pypi_sqlite_cipher-1.0.1.dist-info/LICENSE.txt
pypi_sqlite_cipher-1.0.1.dist-info/METADATA
pypi_sqlite_cipher-1.0.1.dist-info/WHEEL
pypi_sqlite_cipher-1.0.1.dist-info/top_level.txt
pypi_sqlite_cipher-1.0.1.dist-info/RECORD
