Metadata-Version: 2.1
Name: pypi-sqlite-cipher
Version: 1.0.1
Summary: An feature extraction algorithm
Home-page: https://gitee.com/wxb_857_admin/pypi-sqlite-cipher.git
Author: XiaoBai
Author-email: wxok857@foxmail.com
License: MIT Licence
Keywords: pip,pypi_sqlite_cipher
Platform: any
Requires-Dist: pytz (==2021.1)
